[
  {
    "url": "https://app.shomvob.co/single-job-description/?id=20326",
    "job_id": "20326",
    "company_name": "AKIN AIR TRAVELS",
    "job_title": "ржЕржлрж┐рж╕ рж╕рж╣ржХрж╛рж░рзА",
    "location": "Savar",
    "salary": "TK. 10,000-12,000",
    "experience": "6 months - 1 year",
    "education": "S.S.C./Equivalent",
    "employment_type": "Full Time",
    "working_hours": "8 hours per day",
    "deadline": "2026-02-28",
    "date_posted": "2026-02-07",
    "industry": "General Management/Admin",
    "vacancy": 2,
    "shift": "Day Shift",
    "country": null,
    "company_address": "Chowrongi Market, 3rd Foor(Lift-02), Beside Masjid, Savar, Dhaka",
    "job_description": "Responsibilities: Managing daily administrative tasks at the office Maintaining and updating files, documents, and records Receiving phone calls and providing basic information to customers Providing necessary assistance to the ticketing and visa support team Managing office supplies and updating inventory Assisting in mail, courier, and document handling Completing other tasks as per management's instructions Office Location: Savar Bus Stand, Dhaka-1340\n\nRequirements: Minimum educational qualification: Class 8 / SSC Experience as an office assistant is preferable Proficiency in computer operation (MS Word, Excel, Email) is advantageous Proficiency in effective communication in Bengali and English is advantageous Must be smart, hardworking, and responsible Salary and Benefits: Salary: 10,000 to 12,000 Taka Festival allowance Friendly work environment Opportunity for career growth\n\nржЕржлрж┐рж╕рзЗрж░ ржжрзИржиржирзНржжрж┐ржи ржкрзНрж░рж╢рж╛рж╕ржирж┐ржХ ржХрж╛ржЬ ржкрж░рж┐ржЪрж╛рж▓ржирж╛ ржХрж░рж╛ ржлрж╛ржЗрж▓, ржбржХрзБржорзЗржирзНржЯ ржУ рж░рзЗржХрж░рзНржб рж╕ржВрж░ржХрзНрж╖ржг ржУ рж╣рж╛рж▓ржирж╛ржЧрж╛ржж рж░рж╛ржЦрж╛ ржлрзЛржи ржХрж▓ рж░рж┐рж╕рж┐ржн ржХрж░рж╛ ржУ ржХрж╛рж╕рзНржЯржорж╛рж░ржХрзЗ ржкрзНрж░рж╛ржержорж┐ржХ рждржерзНржп ржкрзНрж░ржжрж╛ржи ржЯрж┐ржХрж┐ржЯрж┐ржВ ржУ ржнрж┐рж╕рж╛ рж╕рж╛ржкрзЛрж░рзНржЯ ржЯрж┐ржоржХрзЗ ржкрзНрж░ржпрж╝рзЛржЬржирзАржпрж╝ рж╕рж╣рж╛ржпрж╝рждрж╛ ржкрзНрж░ржжрж╛ржи ржЕржлрж┐рж╕ рж╕рж╛ржоржЧрзНрж░рзА ржмрзНржпржмрж╕рзНржерж╛ржкржирж╛ ржУ ржЗржиржнрзЗржирзНржЯрж░рж┐ ржЖржкржбрзЗржЯ рж░рж╛ржЦрж╛ ржорзЗржЗрж▓, ржХрзБрж░рж┐ржпрж╝рж╛рж░ ржУ ржбржХрзБржорзЗржирзНржЯ ржЖржжрж╛ржи-ржкрзНрж░ржжрж╛ржирзЗ рж╕рж╣рж╛ржпрж╝рждрж╛ ржХрж░рж╛ ржорзНржпрж╛ржирзЗржЬржорзЗржирзНржЯрзЗрж░ ржирж┐рж░рзНржжрзЗрж╢ржирж╛ ржЕржирзБржпрж╛ржпрж╝рзА ржЕржирзНржпрж╛ржирзНржп ржХрж╛ржЬ рж╕ржорзНржкржирзНржи ржХрж░рж╛ ржЕржлрж┐рж╕ рж▓рзЛржХрзЗрж╢ржиржГ рж╕рж╛ржнрж╛рж░ ржмрж╛рж╕ рж╕рзНржЯрж╛ржирзНржб, ржврж╛ржХрж╛-рззрзйрзкрзж"
  },
  {
    "url": "https://app.shomvob.co/single-job-description/?id=20328",
    "job_id": "20328",
    "company_name": "KHAN METRO FORCE S.S LTD",
    "job_title": "Assistant Supervisor",
    "location": "Gulshan, Dhanmondi, Narayanganj, Banani, Jatrabari",
    "salary": "TK. 18,500",
    "experience": "Fresher",
    "education": "Honors/Equivalent",
    "employment_type": "Full Time",
    "working_hours": "",
    "deadline": "2026-02-28",
    "date_posted": "2026-02-07",
    "industry": "Supervisor",
    "vacancy": 95,
    "shift": "Day Shift",
    "country": null,
    "company_address": null,
    "job_description": "Responsibilities: ```html тнР Job Advertisement тнР тнР Position: Assistant Supervisor тнР Location: Various areas within Dhaka тАУ Banani, Gulshan, Dhanmondi, Uttara, Jatrabari, Narayanganj (Main Office/Registration: Savar, Hemayetpur) тнР Duty Hours: Daily 8-10 hours тнР Leave: 1 day off per week Total 3 days off per month тнР Salary: 18,500 BDT (Monthly) тнР Accommodation and Food: тШЕ Accommodation provided free of charge тШЕ Food arrangements available тШЕ An advance of 3,500 BDT will be given for mess expenses in the first month for food тШЕ Deductions will be made from salary in subsequent months тнР Required Documents: тШЕ Photocopy of Voter ID Card тШЕ Chairman's Certificate тШЕ Educational Qualification Certificate тШЕ Passport size photos - 4 copies тШЕ Photocopy of Nominee's ID Card - 1 copy тнР Contact: тШЕ 01324590246 ```\n\nтнР ржирж┐рзЯрзЛржЧ ржмрж┐ржЬрзНржЮржкрзНрждрж┐ тнР тнР ржкржжрзЗрж░ ржирж╛ржо: рж╕рж╣ржХрж╛рж░рзА рж╕рзБржкрж╛рж░ржнрж╛ржЗржЬрж╛рж░ (Assistant Supervisor) тнР ржХрж░рзНржорж╕рзНржерж▓: ржврж╛ржХрж╛рж░ ржоржзрзНржпрзЗ ржмрж┐ржнрж┐ржирзНржи ржПрж▓рж╛ржХрж╛ тАУ ржмржирж╛ржирзА, ржЧрзБрж▓рж╢рж╛ржи, ржзрж╛ржиржоржирзНржбрж┐, ржЙрждрзНрждрж░рж╛, ржпрж╛рждрзНрж░рж╛ржмрж╛ржбрж╝рж┐, ржирж╛рж░рж╛ржпрж╝ржгржЧржЮрзНржЬ (ржкрзНрж░ржзрж╛ржи ржЕржлрж┐рж╕/рж░рзЗржЬрж┐рж╕рзНржЯрзНрж░рзЗрж╢ржи: рж╕рж╛ржнрж╛рж░, рж╣рзЗржорж╛ржпрж╝рзЗрждржкрзБрж░) тнР ржбрж┐ржЙржЯрж┐ рж╕ржоржпрж╝: ржжрзИржирж┐ржХ рзотАУрззрзж ржШржгрзНржЯрж╛ тнР ржЫрзБржЯрж┐: рж╕рж╛ржкрзНрждрж╛рж╣рж┐ржХ рзз ржжрж┐ржи ржЫрзБржЯрж┐ ржорж╛рж╕рзЗ ржорзЛржЯ рзй ржжрж┐ржи ржЫрзБржЯрж┐ тнР ржмрзЗрждржи: рззрзо,рзлрзжрзж ржЯрж╛ржХрж╛ (ржорж╛рж╕рж┐ржХ) тнР ржерж╛ржХрж╛ ржУ ржЦрж╛ржмрж╛рж░: тШЕ ржерж╛ржХрж╛ рж╕ржорзНржкрзВрж░рзНржг ржлрзНрж░рж┐ тШЕ ржЦрж╛ржмрж╛рж░рзЗрж░ рж╕рзБржмрзНржпржмрж╕рзНржерж╛ рж░ржпрж╝рзЗржЫрзЗ тШЕ ржЦрж╛ржмрж╛рж░ ржмрж╛ржмржж ржкрзНрж░ржержо ржорж╛рж╕рзЗ ржорзЗрж╕ ржЦрж░ржЪ рж╣рж┐рж╕рзЗржмрзЗ рзй,рзлрзжрзж ржЯрж╛ржХрж╛ ржПржбржнрж╛ржирзНрж╕ ржжрж┐рждрзЗ рж╣ржмрзЗ тШЕ ржкрж░ржмрж░рзНрждрзА ржорж╛рж╕ржЧрзБрж▓рзЛрждрзЗ рж╕рзНржпрж╛рж▓рж╛рж░рж┐ ржерзЗржХрзЗ ржХрзЗржЯрзЗ ржирзЗржУржпрж╝рж╛ рж╣ржмрзЗ тнР ржкрзНрж░ржпрж╝рзЛржЬржирзАржпрж╝ ржХрж╛ржЧржЬржкрждрзНрж░: тШЕ ржнрзЛржЯрж╛рж░ ржЖржЗржбрж┐ ржХрж╛рж░рзНржбрзЗрж░ ржлржЯрзЛржХржкрж┐ тШЕ ржЪрзЗржпрж╝рж╛рж░ржорзНржпрж╛ржи ржкрж░рж┐ржЪржпрж╝ржкрждрзНрж░ тШЕ рж╢рж┐ржХрзНрж╖рж╛ржЧржд ржпрзЛржЧрзНржпрждрж╛рж░ рж╕рж╛рж░рзНржЯрж┐ржлрж┐ржХрзЗржЯ тШЕ ржкрж╛рж╕ржкрзЛрж░рзНржЯ рж╕рж╛ржЗржЬрзЗрж░ ржЫржмрж┐ тАУ рзк ржХржкрж┐ тШЕ ржиржорж┐ржирж┐рж░ ржЖржЗржбрж┐ ржХрж╛рж░рзНржбрзЗрж░ ржлржЯрзЛржХржкрж┐ тАУ рзз ржХржкрж┐ тнР ржпрзЛржЧрж╛ржпрзЛржЧ: тШЕ 01324590246"
  },
  {
    "url": "https://app.shomvob.co/single-job-description/?id=20339",
    "job_id": "20339",
    "company_name": "Top Notch Cleaning Service",
    "job_title": "ржХрзНрж▓рж┐ржирж╛рж░ (Cleaner)",
    "location": "Mirpur",
    "salary": "TK. 10,000-15,000",
    "experience": "Fresher",
    "education": "Any",
    "employment_type": "Full Time",
    "working_hours": "",
    "deadline": "2026-02-28",
    "date_posted": "2026-02-07",
    "industry": "Household",
    "vacancy": 10,
    "shift": "Day Shift",
    "country": null,
    "company_address": null,
    "job_description": "Responsibilities: Top Notch Cleaning Service is urgently hiring skilled and hardworking cleaners. Interested candidates are invited to apply. Job Description Position: Cleaner Location: Mirpur, Dhaka Duty Hours: 8:00 AM - 7:00 PM Salary: 10,000 - 15,000 BDT (depending on qualifications and experience) Qualifications and Experience Minimum educational qualification: Class 5 / Below Class 8 Experience: 6 months - 1 year (opportunity available for newcomers as well) Must be hardworking and responsible Must have a positive attitude towards working with a team Necessary training will be provided by the company Candidates can join by 15th February or earlierтАФpriority will be given to such applicants Responsibilities Perform cleaning tasks in residential, office, and institutional environments Complete tasks within the designated time Coordinate and work harmoniously with team members Ensure high standards of cleanliness Benefits Festival bonus Partial free lunch facility Annual salary review TA/DA Mobile bill Performance allowance Our Services Full home deep cleaning Sofa deep cleaning Bathroom deep cleaning Kitchen deep cleaning Kitchen hood deep cleaning Chair deep cleaning Contact Address 3/5/C North Pirerbag (60 Ft Road), Kamal Soroni, Mirpur-2, Dhaka-1216, Bangladesh ЁЯУЮ WhatsApp: 01779897190, 01776714760 ЁЯУй Interested candidates can directly send their CV to the WhatsApp number.\n\nTop Notch Cleaning Service-ржП ржЬрж░рзБрж░рж┐ржнрж╛ржмрзЗ ржжржХрзНрж╖ ржУ ржкрж░рж┐рж╢рзНрж░ржорзА ржХрзНрж▓рж┐ржирж╛рж░ ржирж┐ржпрж╝рзЛржЧ ржжрзЗржУржпрж╝рж╛ рж╣ржмрзЗред ржЖржЧрзНрж░рж╣рзА ржкрзНрж░рж╛рж░рзНржерзАржжрзЗрж░ ржирж┐ржХржЯ ржерзЗржХрзЗ ржЖржмрзЗржжржи ржЖрж╣рзНржмрж╛ржи ржХрж░рж╛ рж╣ржЪрзНржЫрзЗред ржкржжрзЗрж░ ржмрж┐ржмрж░ржг ржкржж: ржХрзНрж▓рж┐ржирж╛рж░ рж▓рзЛржХрзЗрж╢ржи: ржорж┐рж░ржкрзБрж░, ржврж╛ржХрж╛ ржбрж┐ржЙржЯрж┐ рж╕ржоржпрж╝: рж╕ржХрж╛рж▓ рзоржЯрж╛ тАУ рж╕ржирзНржзрзНржпрж╛ рзнржЯрж╛ ржмрзЗрждржи: рззрзж,рзжрзжрзж тАУ рззрзл,рзжрзжрзж ржЯрж╛ржХрж╛ (ржпрзЛржЧрзНржпрждрж╛ ржУ ржЕржнрж┐ржЬрзНржЮрждрж╛ ржЕржирзБржпрж╛ржпрж╝рзА) ржпрзЛржЧрзНржпрждрж╛ ржУ ржЕржнрж┐ржЬрзНржЮрждрж╛ ржирзНржпрзВржирждржо рж╢рж┐ржХрзНрж╖рж╛ржЧржд ржпрзЛржЧрзНржпрждрж╛: рзлржо рж╢рзНрж░рзЗржгрзА / рзоржо рж╢рзНрж░рзЗржгрзАрж░ ржирж┐ржЪрзЗ ржЕржнрж┐ржЬрзНржЮрждрж╛: рзм ржорж╛рж╕ тАУ рзз ржмржЫрж░ (ржирждрзБржиржжрзЗрж░ ржЬржирзНржпржУ рж╕рзБржпрзЛржЧ рж░ржпрж╝рзЗржЫрзЗ) ржкрж░рж┐рж╢рзНрж░ржорзА ржУ ржжрж╛ржпрж╝рж┐рждрзНржмрж╢рзАрж▓ рж╣рждрзЗ рж╣ржмрзЗ ржЯрж┐ржорзЗрж░ рж╕ржЩрзНржЧрзЗ ржХрж╛ржЬ ржХрж░рж╛рж░ ржорж╛ржирж╕рж┐ржХрждрж╛ ржерж╛ржХрждрзЗ рж╣ржмрзЗ ржХрзЛржорзНржкрж╛ржирж┐ ржерзЗржХрзЗ ржкрзНрж░рзЯрзЛржЬржирзАрзЯ ржкрзНрж░рж╢рж┐ржХрзНрж╖ржг ржкрзНрж░ржжрж╛ржи ржХрж░рж╛ рж╣ржмрзЗ рззрзл ржлрзЗржмрзНрж░рзБрзЯрж╛рж░рж┐рж░ ржоржзрзНржпрзЗ ржмрж╛ рждрж╛рж░ ржЖржЧрзЗржЗ ржпрзЛржЧржжрж╛ржи ржХрж░рждрзЗ ржкрж╛рж░ржмрзЗржитАФржПржоржи ржкрзНрж░рж╛рж░рзНржерзАржжрзЗрж░ ржЕржЧрзНрж░рж╛ржзрж┐ржХрж╛рж░ ржжрзЗржУрзЯрж╛ рж╣ржмрзЗ ржжрж╛ржпрж╝рж┐рждрзНржмрж╕ржорзВрж╣ ржмрж╛рж╕рж╛, ржЕржлрж┐рж╕ ржУ ржкрзНрж░рж╛рждрж┐рж╖рзНржарж╛ржирж┐ржХ ржкрж░рж┐ржмрзЗрж╢рзЗ ржкрж░рж┐рж╖рзНржХрж╛рж░-ржкрж░рж┐ржЪрзНржЫржирзНржирждрж╛рж░ ржХрж╛ржЬ рж╕ржорзНржкрж╛ржжржи ржХрж░рж╛ ржирж┐рж░рзНржзрж╛рж░рж┐ржд рж╕ржоржпрж╝ ржЕржирзБржпрж╛ржпрж╝рзА ржХрж╛ржЬ рж╕ржорзНржкржирзНржи ржХрж░рж╛ ржЯрж┐ржо рж╕ржжрж╕рзНржпржжрзЗрж░ рж╕ржЩрзНржЧрзЗ рж╕ржоржирзНржмржпрж╝ ржХрж░рзЗ ржХрж╛ржЬ ржХрж░рж╛ ржЙржЪрзНржЪржорж╛ржирзЗрж░ ржкрж░рж┐ржЪрзНржЫржирзНржирждрж╛ ржирж┐рж╢рзНржЪрж┐ржд ржХрж░рж╛ рж╕рзБржмрж┐ржзрж╛рж╕ржорзВрж╣ ржЙрзОрж╕ржм ржмрзЛржирж╛рж╕ ржЖржВрж╢рж┐ржХ ржлрзНрж░рж┐ рж▓рж╛ржЮрзНржЪ рж╕рзБржмрж┐ржзрж╛ ржмрж╛рзОрж╕рж░рж┐ржХ ржмрзЗрждржи рж░рж┐ржнрж┐ржЙ ржЯрж┐/ржП ржорзЛржмрж╛ржЗрж▓ ржмрж┐рж▓ ржкрж╛рж░ржлрж░ржорзЗржирзНрж╕ ржнрж╛рждрж╛ ржЖржорж╛ржжрзЗрж░ рж╕рж╛рж░рзНржнрж┐рж╕рж╕ржорзВрж╣ ржлрзБрж▓ рж╣рзЛржо ржбрж┐ржк ржХрзНрж▓рж┐ржирж┐ржВ рж╕рзЛржлрж╛ ржбрж┐ржк ржХрзНрж▓рж┐ржирж┐ржВ ржмрж╛ржерж░рзБржо ржбрж┐ржк ржХрзНрж▓рж┐ржирж┐ржВ ржХрж┐ржЪрзЗржи ржбрж┐ржк ржХрзНрж▓рж┐ржирж┐ржВ ржХрж┐ржЪрзЗржи рж╣рзБржб ржбрж┐ржк ржХрзНрж▓рж┐ржирж┐ржВ ржЪрзЗрзЯрж╛рж░ ржбрж┐ржк ржХрзНрж▓рж┐ржирж┐ржВ ржпрзЛржЧрж╛ржпрзЛржЧрзЗрж░ ржарж┐ржХрж╛ржирж╛ 3/5/C North Pirerbag (60 Ft Road), Kamal Soroni, Mirpur-2, Dhaka-1216, Bangladesh ЁЯУЮ WhatsApp: 01779897190, 01776714760 ЁЯУй ржЖржЧрзНрж░рж╣рзАрж░рж╛ рж╕рж░рж╛рж╕рж░рж┐ WhatsApp ржиржорзНржмрж░рзЗ CV ржкрж╛ржарж╛рждрзЗ ржкрж╛рж░ржмрзЗржиред"
  },
  {
    "url": "https://app.shomvob.co/single-job-description/?id=20330",
    "job_id": "20330",
    "company_name": "KHAN METRO FORCE S.S LTD",
    "job_title": "Recruiting Officer",
    "location": "Gulshan, Dhanmondi, Narayanganj, Banani, Jatrabari",
    "salary": "TK. 20,000-25,000",
    "experience": "Fresher",
    "education": "S.S.C./Equivalent",
    "employment_type": "Full Time",
    "working_hours": "10 hours per day",
    "deadline": "2026-02-28",
    "date_posted": "2026-02-07",
    "industry": "Media/Advertisement/Event Mgt.",
    "vacancy": 30,
    "shift": "Day Shift",
    "country": null,
    "company_address": "Savar Haymaytpur",
    "job_description": "Responsibilities: ```html тнР Job Advertisement тнР тнР Position: Recruiting Officer тнР Number of Positions: 30 (Male & Female) тнР Duty Time: 8 hours daily тнР Educational Qualification: Minimum S.S.C. (Secondary School Certificate) тнР Salary: (Negotiable) тнР Leave: Weekly off - Every Friday тнР Bonus: 2 annual Eid bonuses тнР Accommodation and Food: тШЕ Accommodation provided free of charge тШЕ Food arrangements available тШЕ An advance of 3,500 taka will be given for the first month's mess expenses тШЕ Subsequent months' mess expenses will be deducted from salary тнР Contact: тШЕ 01324590246 ```\n\nтнР ржирж┐рзЯрзЛржЧ ржмрж┐ржЬрзНржЮржкрзНрждрж┐ тнР тнР ржкржжрзЗрж░ ржирж╛ржо: рж░рж┐ржХрзНрж░рзБржЯрж┐ржВ ржЕржлрж┐рж╕рж╛рж░ (Recruiting Officer) тнР ржкржжрж╕ржВржЦрзНржпрж╛: рзйрзж ржЬржи (ржЫрзЗрж▓рзЗ ржУ ржорзЗрзЯрзЗ) тнР ржбрж┐ржЙржЯрж┐ ржЯрж╛ржЗржо: ржжрзИржирж┐ржХ рзо ржШржгрзНржЯрж╛ тнР рж╢рж┐ржХрзНрж╖рж╛ржЧржд ржпрзЛржЧрзНржпрждрж╛: ржирзНржпрзВржирждржо ржПрж╕ржПрж╕рж╕рж┐ (S.S.C.) тнР ржмрзЗрждржи: (ржЖрж▓рзЛржЪржирж╛ рж╕рж╛ржкрзЗржХрзНрж╖рзЗ) тнР ржЫрзБржЯрж┐: рж╕рж╛ржкрзНрждрж╛рж╣рж┐ржХ ржмржирзНржз тАУ ржкрзНрж░рждрж┐ рж╢рзБржХрзНрж░ржмрж╛рж░ тнР ржмрзЛржирж╛рж╕: ржмрж╛рзОрж╕рж░рж┐ржХ рзиржЯрж┐ ржИржж ржмрзЛржирж╛рж╕ тнР ржерж╛ржХрж╛ ржУ ржЦрж╛ржмрж╛рж░: тШЕ ржерж╛ржХрж╛ рж╕ржорзНржкрзВрж░рзНржг ржлрзНрж░рж┐ тШЕ ржЦрж╛ржмрж╛рж░рзЗрж░ рж╕рзБржмрзНржпржмрж╕рзНржерж╛ рж░ржпрж╝рзЗржЫрзЗ тШЕ ржЦрж╛ржмрж╛рж░ ржмрж╛ржмржж ржкрзНрж░ржержо ржорж╛рж╕рзЗ ржорзЗрж╕ ржЦрж░ржЪ рж╣рж┐рж╕рзЗржмрзЗ рзй,рзлрзжрзж ржЯрж╛ржХрж╛ ржПржбржнрж╛ржирзНрж╕ ржжрж┐рждрзЗ рж╣ржмрзЗ тШЕ ржкрж░ржмрж░рзНрждрзА ржорж╛рж╕ржЧрзБрж▓рзЛрждрзЗ рж╕рзНржпрж╛рж▓рж╛рж░рж┐ ржерзЗржХрзЗ ржХрзЗржЯрзЗ ржирзЗржУржпрж╝рж╛ рж╣ржмрзЗ тнР ржпрзЛржЧрж╛ржпрзЛржЧ: тШЕ 01324590246"
  },
  {
    "url": "https://app.shomvob.co/single-job-description/?id=20333",
    "job_id": "20333",
    "company_name": "Chaldal Ltd",
    "job_title": "ржбрзЗрж▓рж┐ржнрж╛рж░рж┐ ржЕрзНржпрж╛рж╕рзЛрж╕рж┐ржпрж╝рзЗржЯ ржкржжрзЗ ржирж┐ржпрж╝рзЛржЧ",
    "location": "Uttara, Notun Bajar, Panthapath, Rajarbagh, Rampura",
    "salary": "TK. 8,360-11,960",
    "experience": "Fresher",
    "education": "Any",
    "employment_type": "Full Time",
    "working_hours": "12 hours per day",
    "deadline": "2026-03-07",
    "date_posted": "2026-02-07",
    "industry": "Deliveryman",
    "vacancy": 30,
    "shift": "Day Shift",
    "country": null,
    "company_address": "Banani, Dhaka",
    "job_description": "Responsibilities: Rajarbag, Rampura, Dhalibari (Vatara), Panthapath, Uttara, Hazaribagh areas have delivery associates vacancies Salary: 8360 - 11960 Taka Benefits: 1 day off after every 2 days, 10 days off per month. Shifts from 7 am, 9 am, and 10:45 am. 12-hour duty. 1-hour break time Delivery Bonus: A bonus of 10 Taka is given for each delivery from 18 to 24 deliveries. After 24 deliveries, a bonus of 15 Taka is given for all deliveries. Incentive arrangements are available Other benefits: Six-monthly salary increment. Twice a year festival allowance. 14 days sick leave per year after six months. 11 days festival leave per year after six months. 12 days annual leave per year after six months. 10 days casual leave per year after six months\n\nRequirements: Terms and Conditions: The individual must be 18 years old or above as per birth registration or national ID card.\n\nрж░рж╛ржЬрж╛рж░ржмрж╛ржЧ, рж░рж╛ржоржкрзБрж░рж╛, ржврж╛рж▓рзАржмрж╛ржбрж╝рж┐ (ржнрж╛ржЯрж╛рж░рж╛), ржкрж╛ржирзНржержкрже, ржЙрждрзНрждрж░рж╛, рж╣рж╛ржЬрж╛рж░рзАржмрж╛ржЧ ржПрж░рж┐ржпрж╝рж╛ржЧрзБрж▓рзЛрждрзЗ ржбрзЗрж▓рж┐ржнрж╛рж░рж┐ ржЕрзНржпрж╛рж╕рзЛрж╕рж┐ржпрж╝рзЗржЯ ржП ржнрзНржпрж╛ржХрзЗржирзНрж╕рж┐ ржЖржЫрзЗ ржмрзЗрждржи: рзорзйрзмрзж - рззрззрзпрзмрзж ржЯрж╛ржХрж╛ рж╕рзБржмрж┐ржзрж╛ рж╕ржорзВрж╣: рзи ┬аржжрж┐ржи ржкрж░ ржкрж░ рзз ржжрж┐ржи, ржорж╛рж╕рзЗ рззрзж ┬аржжрж┐ржи ржЫрзБржЯрж┐ред рж╕ржХрж╛рж▓ рзнржЯрж╛ , рзпржЯрж╛ ржПржмржВ рззрзж:рзкрзл ржерзЗржХрзЗ рж╢рж┐ржлржЯред рззрзи ржШржирзНржЯрж╛ ржбрж┐ржЙржЯрж┐ ред рзз ржШржирзНржЯрж╛ ржмрзНрж░рзЗржХ ржЯрж╛ржЗржо ржбрзЗрж▓рж┐ржнрж╛рж░рж┐ ржмрзЛржирж╛рж╕ржГ рззрзо ржерзЗржХрзЗ рзирзк ржЯрж╛ ржкрж░рзНржпржирзНржд ржкрзНрж░рждрж┐ржЯрж┐ ржбрзЗрж▓рж┐ржнрж╛рж░рж┐рж░ ржПрж░ ржЬржирзНржп рззрзж ржЯрж╛ржХрж╛ ржХрж░рзЗ ржмрзЛржирж╛рж╕ ржжрзЗржУрзЯрж╛ рж╣рзЯред рзирзк ржПрж░ ржкрж░ рж╕ржХрж▓ ржбрзЗрж▓рж┐ржнрж╛рж░рж┐ ржПрж░ ржЬржирзНржп рззрзл ржЯрж╛ржХрж╛ ржХрж░рзЗ ржмрзЛржирж╛рж╕ ржжрзЗржУрзЯрж╛ рж╣рзЯред ржЗржирж╕рзЗржирзНржЯрж┐ржн ржПрж░ ржмрзНржпржмрж╕рзНржерж╛ рж░ржпрж╝рзЗржЫрзЗ ржЕржирзНржпрж╛ржирзНржп рж╕рзБржмрж┐ржзрж╛ рж╕ржорзБрж╣ржГ ржЫржпрж╝ ржорж╛рж╕ ржкрж░ ржмрзЗрждржи ржмрзГржжрзНржзрж┐ ржкрж╛ржмрзЗред ржмржЫрж░рзЗ ржжрзБржЗржмрж╛рж░ ржЙрзОрж╕ржм ржнрж╛рждрж╛ ржжрзЗржпрж╝рж╛ рж╣ржпрж╝ред ржЫржпрж╝ ржорж╛рж╕ ржкрж░ ржерзЗржХрзЗ ржмржЫрж░рзЗ рззрзк ржжрж┐ржи ржЕрж╕рзБрж╕рзНржерждрж╛ ржЬржирж┐ржд ржЫрзБржЯрж┐ ржжрзЗржпрж╝рж╛ рж╣ржпрж╝ред ржЫржпрж╝ ржорж╛рж╕ ржкрж░ ржерзЗржХрзЗ ржмржЫрж░рзЗ рззрзз ржжрж┐ржи ржЙрзОрж╕ржм ржЫрзБржЯрж┐ ржжрзЗржпрж╝рж╛ рж╣ржпрж╝ред ржЫржпрж╝ ржорж╛рж╕ ржкрж░ ржерзЗржХрзЗ ржмржЫрж░рзЗ рззрзи ржжрж┐ржи ржмрзЗрждржиржнрзЛржЧрзА ржЫрзБржЯрж┐ ржжрзЗржпрж╝рж╛ рж╣ржпрж╝ред ржЫржпрж╝ ржорж╛рж╕ ржкрж░ ржерзЗржХрзЗ ржмржЫрж░рзЗ рззрзж ржжрж┐ржи ржирзИржорж┐рждрзНрждрж┐ржХ ржЫрзБржЯрж┐ ржжрзЗржпрж╝рж╛ рж╣ржпрж╝"
  },
  {
    "url": "https://app.shomvob.co/single-job-description/?id=20341",
    "job_id": "20341",
    "company_name": "RANOT ARTISAN GROUP",
    "job_title": "Production Assistant тАУ Premium Chocolate & Pastry Brand",
    "location": "Demra",
    "salary": "TK. 8,000-12,000",
    "experience": "Fresher",
    "education": "S.S.C./Equivalent",
    "employment_type": "Full Time",
    "working_hours": "8 hours per day",
    "deadline": "2026-03-08",
    "date_posted": "2026-02-07",
    "industry": "Garments - Production/Operator/Technician",
    "vacancy": 20,
    "shift": "Day Shift",
    "country": null,
    "company_address": "17/1,Konapara, Demra, Dhaka 1262",
    "job_description": "Responsibilities: Key Responsibilities\n\n- Production Support: Assist the production team in crafting high-quality chocolates and pastries under professional guidance.\n- Batching & Preparation: Precisely measure, weigh, and organize ingredients for production batches according to established recipes.\n- Packaging & Quality Control: Carefully pack finished products in premium packaging, ensuring they are aesthetically presented and ready for delivery.\n- Workplace Hygiene: Maintain strict hygiene and cleanliness standards in the workspace to ensure a food-safe environment.\n- Tool & Equipment Handling: Handle delicate kitchen tools and machinery with care, ensuring they are cleaned and stored properly after use.\n\nOperational Support: Support daily logistics and operational tasks to ensure a smooth production flow from start to finish.\n\nRequirements: Safety & Compliance\n\n- Strict Sanitation: Adhere to all personal hygiene protocols, including the mandatory use of hairnets, gloves, and aprons.\n- Equipment Safety: Follow safety instructions carefully when operating machinery or handling sharp/hot equipment.\n- Safe Handling: Practice safe ingredient storage and handling to prevent cross-contamination.\n- Environmental Safety: Maintain a clutter-free workspace to prevent accidents and ensure a safe working environment for the whole team.\n\nCandidate Profile\n\n- Attitude: Honest, punctual, and highly disciplined.\n- Education: Minimum SSC preferred.\n- Experience: Previous kitchen, bakery, or packing experience is a plus, but freshers are highly encouraged to apply.\n- Training: Full professional training will be provided.\n\nWhat We Offer\n\n- Competitive entry-level salary.\n- Hands-on skill development in a premium work environment.\n- Long-term career growth opportunities.\n\nKey Responsibilities Production Support: Assist the production team in crafting high-quality chocolates and pastries under professional guidance. Batching & Preparation: Precisely measure, weigh, and organize ingredients for production batches according to established recipes. Packaging & Quality Control: Carefully pack finished products in premium packaging, ensuring they are aesthetically presented and ready for delivery. Workplace Hygiene: Maintain strict hygiene and cleanliness standards in the workspace to ensure a food-safe environment. Tool & Equipment Handling: Handle delicate kitchen tools and machinery with care, ensuring they are cleaned and stored properly after use. Operational Support: Support daily logistics and operational tasks to ensure a smooth production flow from start to finish."
  },
  {
    "url": "https://app.shomvob.co/single-job-description/?id=20334",
    "job_id": "20334",
    "company_name": "HealthOS Limited",
    "job_title": "Delivery Coordinator",
    "location": "Mohammadpur",
    "salary": "TK. 18,000-22,000",
    "experience": "6 months - 1 year",
    "education": "Honors/Equivalent",
    "employment_type": "Full Time",
    "working_hours": "8 hours per day",
    "deadline": "2026-03-07",
    "date_posted": "2026-02-07",
    "industry": "Garments - Production/Operator/Technician",
    "vacancy": 6,
    "shift": "Day Shift",
    "country": null,
    "company_address": "HealthOS Ltd, Khan ABC Tradeplex, Road-02, Dhanmondi, Dhaka, 1205, Dhaka, Bangladesh",
    "job_description": "Responsibilities: Key Responsibilities:\n- Coordinate daily delivery schedules, routes, and assignments for delivery staff.\n- Ensure timely and accurate delivery of products to clients.\n- Monitor delivery progress and resolve issues such as delays, complaints, or misdeliveries.\n- Maintain communication with warehouse & logistics.\n- Track inventory and delivery records, ensuring proper documentation is maintained.\n- Supervise and support delivery staff to maintain performance standards.\n- Ensure compliance with company policies, safety rules, and operational guidelines.\n- Generate daily delivery reports for management.\n\nQualifications & Skills:\n- Bachelor's degree in any discipline.\n- Minimum 1 year of experience in logistics, supply chain, or delivery coordination (Freshers are also encouraged to apply).\n- Strong organizational and time management skills.\n- Ability to handle multiple tasks and work under pressure.\n- Good communication and leadership skills.\n- Proficiency in MS Office.\n\nKey Responsibilities: Coordinate daily delivery schedules, routes, and assignments for delivery staff. Ensure timely and accurate delivery of products to clients. Monitor delivery progress and resolve issues such as delays, complaints, or misdeliveries. Maintain communication with warehouse & logistics. Track inventory and delivery records, ensuring proper documentation is maintained. Supervise and support delivery staff to maintain performance standards. Ensure compliance with company policies, safety rules, and operational guidelines. Generate daily delivery reports for management. Qualifications & Skills: Bachelor degree in any discipline. Minimum 1 years of experience in logistics, supply chain, or delivery coordination (Freshers Are also encourage to apply) Strong organizational and time management skills. Ability to handle multiple tasks and work under pressure. Good communication and leadership skills. Proficiency in MS Office."
  },
  {
    "url": "https://app.shomvob.co/single-job-description/?id=20327",
    "job_id": "20327",
    "company_name": "Piyas International Ltd",
    "job_title": "рж╕рзЗрж▓рж╕ рж░рж┐ржкрзНрж░рзЗржЬрзЗржирзНржЯрзЗржЯрж┐ржн (SR)",
    "location": "Jessore",
    "salary": "TK. 12,000-14,000",
    "experience": "6 months - 1 year",
    "education": "H.S.C./Equivalent",
    "employment_type": "Full Time",
    "working_hours": "8 hours per day",
    "deadline": "2026-03-07",
    "date_posted": "2026-02-07",
    "industry": "Sales/Marketing",
    "vacancy": 10,
    "shift": "Day Shift",
    "country": null,
    "company_address": "Jessore, Bangladesh",
    "job_description": "Responsibilities: In an expanding production company, urgent recruitment will be done for skilled and hardworking sales representatives in the Household Care section.\n\nЁЯУЛ Product Categories:\n1. Liquid Dishwash\n2. Toilet Cleaner\n3. Vixol/Tile Cleaner\n4. Dam Finish/Pipe and Tank Cleaner\n\nMain Responsibilities:\nMarket Expansion: Visiting various markets according to the designated route to collect product orders from hardware and hardware stores.\n\nPresentation: Demonstrating product samples to retailers and explaining the quality and efficiency accurately.\n\nInstitutional Sales: Contacting various restaurants, cafes, hotels, and hospitals to complete deals.\n\nRelationship Development: Maintaining good relationships with existing customers and collecting feedback or reports on products regularly.\n\nRequirements: тАЛЁЯТ╕ Salary and Benefits: тАМтАЛBasic Salary: 12,000-14,000 BDT. тАМтАЛTA/DA (Travel Allowance): 2,500-4,000 BDT. тАМтАЛIncentive: 6,000-8,000 BDT (Based on achieving targets). тАМтАЛBonus: 2 festival bonuses per year. тАМтАЛSalary Increment: Salary review based on annual performance. тАЛтЩ╗я╕П Applicant Qualifications: тАМтАЛEducational Qualification: Minimum HSC or equivalent (relaxable for experienced candidates). тАМтАЛSkills: Must have the ability to communicate effectively and persuade customers to make purchases. тАМтАЛTransportation: Preference will be given if the candidate has a personal motorcycle (with papers) or a bicycle. тАМтАЛExperience: At least 2 years of experience in the relevant field. However, skilled freshers are also encouraged to apply. тАЛNote: > * Freshers will have a probationary period of 3 months with a slightly lower basic salary. тАЛPreference will be given to smart and proactive candidates.\n\nржПржХржЯрж┐ ржХрзНрж░ржоржмрж░рзНржзржорж╛ржи ржЙрзОржкрж╛ржжржиржХрж╛рж░рзА ржкрзНрж░рждрж┐рж╖рзНржарж╛ржирзЗрж░ ржХрзНрж▓рж┐ржирж┐ржВ ржЖржЗржЯрзЗржо (Household Care) рж╕рзЗржХрж╢ржирзЗ ржЬрж░рзБрж░рж┐ ржнрж┐рждрзНрждрж┐рждрзЗ ржХрж┐ржЫрзБ рж╕ржВржЦрзНржпржХ ржжржХрзНрж╖ ржУ ржкрж░рж┐рж╢рзНрж░ржорзА рж╕рзЗрж▓рж╕ рж░рж┐ржкрзНрж░рзЗржЬрзЗржирзНржЯрзЗржЯрж┐ржн ржирж┐рзЯрзЛржЧ ржжрзЗржУрзЯрж╛ рж╣ржмрзЗред тАЛЁЯУЛ ржкржгрзНржпрзЗрж░ ржХрзНржпрж╛ржЯрж╛ржЧрж░рж┐: тАЛрзз. рж▓рж┐ржХрзБржЗржб ржбрж┐рж╢ржУрзЯрж╛рж╢ рзи. ржЯрзЯрж▓рзЗржЯ ржХрзНрж▓рж┐ржирж╛рж░ рзй. ржнрж┐ржХрзНрж╕рж▓ / ржЯрж╛ржЗрж▓рж╕ ржХрзНрж▓рж┐ржирж╛рж░ рзк. ржбрзНржпрж╛ржо ржлрж┐ржирж┐рж╢ / ржкрж╛ржЗржк ржУ ржЯрзНржпрж╛ржВржХ ржХрзНрж▓рж┐ржирж╛рж░ ржкрзНрж░ржзрж╛ржи ржжрж╛рзЯрж┐рждрзНржмрж╕ржорзВрж╣ : тАМтАЛржмрж╛ржЬрж╛рж░ рж╕ржорзНржкрзНрж░рж╕рж╛рж░ржг: ржирж┐рж░рзНржзрж╛рж░рж┐ржд рж░рзБржЯ ржЕржирзБржпрж╛рзЯрзА ржмрж┐ржнрж┐ржирзНржи ржмрж╛ржЬрж╛рж░ ржкрж░рж┐ржжрж░рзНрж╢ржи ржХрж░рзЗ ржорзБржжрж┐ ржУ рж╣рж╛рж░рзНржбржУрзЯрзНржпрж╛рж░ ржжрзЛржХрж╛ржи ржерзЗржХрзЗ ржкржгрзНржпрзЗрж░ ржЕрж░рзНржбрж╛рж░ рж╕ржВржЧрзНрж░рж╣ ржХрж░рж╛ред тАМтАЛржкрзНрж░ржжрж░рзНрж╢ржи: рж░рж┐ржЯрзЗржЗрж▓рж╛рж░ржжрзЗрж░ ржХрж╛ржЫрзЗ ржкржгрзНржпрзЗрж░ рж╕рзНржпрж╛ржорзНржкрж▓ ржкрзНрж░ржжрж░рзНрж╢ржи ржПржмржВ ржЧрзБржгржЧржд ржорж╛ржи ржУ ржХрж╛рж░рзНржпржХрзНрж╖ржорждрж╛ рж╕ржарж┐ржХржнрж╛ржмрзЗ ржмрзБржЭрж┐рзЯрзЗ ржмрж▓рж╛ред тАМтАЛржкрзНрж░рж╛рждрж┐рж╖рзНржарж╛ржирж┐ржХ рж╕рзЗрж▓рж╕: ржмрж┐ржнрж┐ржирзНржи рж░рзЗрж╕рзНржЯрзБрж░рзЗржирзНржЯ, ржХрзНржпрж╛ржлрзЗ, рж╣рзЛржЯрзЗрж▓ ржПржмржВ рж╣рж╛рж╕ржкрж╛рждрж╛рж▓рзЗ ржпрзЛржЧрж╛ржпрзЛржЧ ржХрж░рзЗ ржбрж┐рж▓ рж╕ржорзНржкржирзНржи ржХрж░рж╛ред тАМтАЛрж╕ржорзНржкрж░рзНржХ ржЙржирзНржирзЯржи: ржмрж┐ржжрзНржпржорж╛ржи ржХрзНрж░рзЗрждрж╛ржжрзЗрж░ рж╕рж╛ржерзЗ рж╕рзБрж╕ржорзНржкрж░рзНржХ ржмржЬрж╛рзЯ рж░рж╛ржЦрж╛ ржПржмржВ ржирж┐рзЯржорж┐ржд ржкржгрзНржпрзЗрж░ ржлрж┐ржбржмрзНржпрж╛ржХ ржмрж╛ рж░рж┐ржкрзЛрж░рзНржЯ рж╕ржВржЧрзНрж░рж╣ ржХрж░рж╛ред тАЛ"
  },
  {
    "url": "https://app.shomvob.co/single-job-description/?id=20329",
    "job_id": "20329",
    "company_name": "Piyas International Ltd",
    "job_title": "ржбрзЗрж▓рж┐ржнрж╛рж░рж┐ ржорзНржпрж╛ржи (Delivery Man)",
    "location": "Jessore",
    "salary": "ржмрзЗрждржи ржЖрж▓рзЛржЪржирж╛ рж╕рж╛ржкрзЗржХрзНрж╖рзЗ",
    "experience": "6 months - 1 year",
    "education": "< Class 8",
    "employment_type": "Full Time",
    "working_hours": "8 hours per day",
    "deadline": "2026-03-07",
    "date_posted": "2026-02-07",
    "industry": "Deliveryman",
    "vacancy": 5,
    "shift": "Day Shift",
    "country": null,
    "company_address": "Jessore, Bangladesh",
    "job_description": "Responsibilities: Our company will hire several diligent delivery men to ensure that our company's cleaning products (dishwashers, toilet cleaners, etc.) are delivered to customers and retailers on time and with care. ЁЯУЛ Product list: 1. Liquid dishwasher 2. Toilet cleaner 3. Vixol / tiles cleaner 4. Dam finish / pipe and tank cleaner ЁЯФ╣ Main responsibilities: Product delivery: Receive products from the warehouse according to daily orders and deliver them to the correct destination (muddy shop, hardware store, or institution). Money collection: Collect the correct amount as per the invoice at the end of product delivery and report it to the office at the end of the day. Product safety: Take special care to ensure that liquid or cleaner products do not leak or get damaged during transportation. Van/bicycle operation: Operate the company-provided van for product delivery. Conduct: Maintain a courteous and professional conduct with customers and retailers.\n\nRequirements: тАЛЁЯТ╕ Salary and Benefits: тАМтАЛBasic salary: To be discussed. тАМтАЛDaily allowance: Fixed allowance for daily commute and expenses. тАМтАЛBonus: Yearly bonus on 2 occasions. тАМтАЛOthers: Special incentives for achieving specific targets. тАЛтЩ╗я╕П Applicant Qualifications: тАМтАЛEducational Qualification: Minimum HSC/SSC or equivalent. тАМтАЛPhysical Ability: Must have physical strength to handle loading/unloading of goods and perform prolonged tasks. тАМтАЛArea Familiarity: Should have a good understanding of local roads and markets. тАМтАЛTransportation: Must know how to drive a motorbike or auto-rickshaw. тАМтАЛReliability: Must maintain 100% honesty and integrity in financial transactions.\n\nржЖржорж╛ржжрзЗрж░ ржХрзЛржорзНржкрж╛ржирж┐рж░ ржЙрзОржкрж╛ржжрж┐ржд ржХрзНрж▓рж┐ржирж┐ржВ ржкржгрзНржпрж╕ржорзВрж╣ (ржбрж┐рж╢ржУрзЯрж╛рж╢, ржЯрзЯрж▓рзЗржЯ ржХрзНрж▓рж┐ржирж╛рж░ ржЗрждрзНржпрж╛ржжрж┐) рж╕ржарж┐ржХ рж╕ржорзЯрзЗ ржПржмржВ ржпрждрзНржирж╕рж╣ржХрж╛рж░рзЗ ржХрж╛рж╕рзНржЯржорж╛рж░ ржУ ржжрзЛржХрж╛ржиржжрж╛рж░рзЗрж░ ржХрж╛ржЫрзЗ ржкрзМржБржЫрзЗ ржжрзЗржУрзЯрж╛рж░ ржЬржирзНржп ржХрж┐ржЫрзБ рж╕ржВржЦрзНржпржХ ржХрж░рзНржоржа ржбрзЗрж▓рж┐ржнрж╛рж░рж┐ ржорзНржпрж╛ржи ржирж┐рзЯрзЛржЧ ржжрзЗржУрзЯрж╛ рж╣ржмрзЗред тАЛЁЯУЛ ржкржгрзНржпрзЗрж░ рждрж╛рж▓рж┐ржХрж╛: тАЛрзз. рж▓рж┐ржХрзБржЗржб ржбрж┐рж╢ржУрзЯрж╛рж╢ рзи. ржЯрзЯрж▓рзЗржЯ ржХрзНрж▓рж┐ржирж╛рж░ рзй. ржнрж┐ржХрзНрж╕рж▓ / ржЯрж╛ржЗрж▓рж╕ ржХрзНрж▓рж┐ржирж╛рж░ рзк. ржбрзНржпрж╛ржо ржлрж┐ржирж┐рж╢ / ржкрж╛ржЗржк ржУ ржЯрзНржпрж╛ржВржХ ржХрзНрж▓рж┐ржирж╛рж░ тАЛЁЯФ╣ ржкрзНрж░ржзрж╛ржи ржжрж╛рзЯрж┐рждрзНржмрж╕ржорзВрж╣: тАМтАЛржкржгрзНржп ржбрзЗрж▓рж┐ржнрж╛рж░рж┐: ржкрзНрж░рждрж┐ржжрж┐ржирзЗрж░ ржЕрж░рзНржбрж╛рж░ ржЕржирзБржпрж╛рзЯрзА ржЧрзБржжрж╛ржо (Warehouse) ржерзЗржХрзЗ ржкржгрзНржп ржмрзБржЭрзЗ ржирзЗржУрзЯрж╛ ржПржмржВ рждрж╛ рж╕ржарж┐ржХ ржЧржирзНрждржмрзНржпрзЗ (ржорзБржжрж┐ ржжрзЛржХрж╛ржи, рж╣рж╛рж░рзНржбржУрзЯрзНржпрж╛рж░ ржжрзЛржХрж╛ржи ржмрж╛ ржкрзНрж░рждрж┐рж╖рзНржарж╛ржи) ржкрзМржБржЫрзЗ ржжрзЗржУрзЯрж╛ред тАМтАЛржЯрж╛ржХрж╛ рж╕ржВржЧрзНрж░рж╣: ржкржгрзНржп ржбрзЗрж▓рж┐ржнрж╛рж░рж┐ рж╢рзЗрж╖рзЗ ржЗржиржнрзЯрзЗрж╕ ржЕржирзБржпрж╛рзЯрзА рж╕ржарж┐ржХ ржорзВрж▓рзНржп рж╕ржВржЧрзНрж░рж╣ ржХрж░рж╛ ржПржмржВ ржжрж┐ржирж╢рзЗрж╖рзЗ ржЕржлрж┐рж╕рзЗ ржмрзБржЭрж┐рзЯрзЗ ржжрзЗржУрзЯрж╛ред тАМтАЛржкржгрзНржпрзЗрж░ рж╕рзБрж░ржХрзНрж╖рж╛: рж▓рж┐ржХрзБржЗржб ржмрж╛ ржХрзНрж▓рж┐ржирж╛рж░ ржЬрж╛рждрзАрзЯ ржкржгрзНржпржЧрзБрж▓рзЛ ржпрзЗржи ржкрж░рж┐ржмрж╣ржирзЗрж░ рж╕ржорзЯ ржлрзЗржЯрзЗ ржирж╛ ржпрж╛рзЯ ржмрж╛ рж▓рж┐ржХ ржирж╛ рж╣рзЯ, рж╕рзЗржжрж┐ржХрзЗ ржмрж┐рж╢рзЗрж╖ ржЦрзЗрзЯрж╛рж▓ рж░рж╛ржЦрж╛ред тАМтАЛржнрзНржпрж╛ржи/ржмрж╛ржЗрж╕рж╛ржЗржХрзЗрж▓ ржкрж░рж┐ржЪрж╛рж▓ржирж╛: ржХрзЛржорзНржкрж╛ржирж┐рж░ ржжрзЗржУрзЯрж╛ ржнрзНржпрж╛ржи┬а ржЪрж╛рж▓рж┐рзЯрзЗ ржкржгрзНржп ржбрзЗрж▓рж┐ржнрж╛рж░рж┐ ржХрж░рж╛ред тАМтАЛржЖржЪрж░ржг: ржХрж╛рж╕рзНржЯржорж╛рж░ ржУ ржжрзЛржХрж╛ржиржжрж╛рж░ржжрзЗрж░ рж╕рж╛ржерзЗ ржмрж┐ржирзЯрзА ржУ ржкрзЗрж╢рж╛ржжрж╛рж░ ржЖржЪрж░ржг ржмржЬрж╛рзЯ рж░рж╛ржЦрж╛ред"
  },
  {
    "url": "https://app.shomvob.co/single-job-description/?id=20325",
    "job_id": "20325",
    "company_name": "Tasnia Overseas",
    "job_title": " Marketing Officer",
    "location": "Banani",
    "salary": "ржмрзЗрждржи ржЖрж▓рзЛржЪржирж╛ рж╕рж╛ржкрзЗржХрзНрж╖рзЗ",
    "experience": "6 months - 1 year",
    "education": "H.S.C./Equivalent",
    "employment_type": "Full Time",
    "working_hours": "9 hours per day",
    "deadline": "2026-03-07",
    "date_posted": "2026-02-07",
    "industry": "Sales/Marketing",
    "vacancy": 5,
    "shift": "Day Shift",
    "country": null,
    "company_address": "House# 79, 6th Floor, New Airport Road,Banani,Chairman Bari, Dhaka, Bangladesh",
    "job_description": "Responsibilities: 1. Client Engagement (Relationship Building):\nUnderstanding the needs and expectations related to visa processing of clients, creating and maintaining a good relationship with them.\nMaintaining direct communication with clients and guiding them through the entire visa application process, providing solutions to any questions or issues.\n\n2. Marketing Strategy Development:\nCollaborating with the marketing team to create and implement effective marketing plans to attract new clients.\nAnalyzing market trends and competitors' activities to identify opportunities for improvement.\n\n3. Service Promotion:\nCreating attractive brochures, presentations, and social media content in simple language to explain the benefits of visa processing services.\nCreating awareness among potential clients through promotional events, webinars, and workshops.\n\n4. Analysis of Client Needs:\nUnderstanding the needs of each client and customizing services accordingly to make them feel valued.\nProviding detailed information about visa types, timelines, required documents, and potential challenges.\n\n5. Time Management and Process Optimization:\nCreating a specific timeline for each client's visa process and providing regular updates.\nCollaborating with the internal team to streamline the entire process for ease and efficiency.\n\n6. Feedback and Improvement:\nCollecting and analyzing client feedback to determine areas for service improvement.\nImplementing changes based on feedback to enhance client satisfaction and trust.\n\n7. Reporting and Analytics:\nGenerating regular reports on marketing performance, client numbers, and satisfaction.\nVerifying the success of marketing campaigns through data analysis and making decisions for future planning accordingly.\n\nRequirements: Proficient communication skills (in both Bengali and English) Prior experience in visa processing or client service is advantageous Mentality to engage with clients in a professional and empathetic manner Interest and experience in marketing strategy and event management Proficiency in social media, presentation, and content creation Must be skilled in time management and multitasking A proactive and focused mindset in problem-solving Understanding of data analysis and reporting is required Interest in participating in and managing events, workshops, or webinars Commitment to long-term work and dedication to professional development\n\nрзз. ржХрзНрж▓рж╛рзЯрзЗржирзНржЯ ржПржиржЧрзЗржЬржорзЗржирзНржЯ (рж╕ржорзНржкрж░рзНржХ ржЧржаржи): ржХрзНрж▓рж╛рзЯрзЗржирзНржЯржжрзЗрж░ ржнрж┐рж╕рж╛ ржкрзНрж░рж╕рзЗрж╕рж┐ржВ рж╕ржВржХрзНрж░рж╛ржирзНржд ржЪрж╛рж╣рж┐ржжрж╛ ржУ ржкрзНрж░рждрзНржпрж╛рж╢рж╛ ржмрзБржЭрзЗ, рждрж╛ржжрзЗрж░ рж╕ржЩрзНржЧрзЗ ржнрж╛рж▓рзЛ рж╕ржорзНржкрж░рзНржХ рждрзИрж░рж┐ ржУ ржзрж░рзЗ рж░рж╛ржЦрж╛ред ржХрзНрж▓рж╛рзЯрзЗржирзНржЯржжрзЗрж░ рж╕ржЩрзНржЧрзЗ рж╕рж░рж╛рж╕рж░рж┐ ржпрзЛржЧрж╛ржпрзЛржЧ рж░рж╛ржЦрж╛ ржПржмржВ ржкрзБрж░рзЛ ржнрж┐рж╕рж╛ ржЕрзНржпрж╛ржкрзНрж▓рж┐ржХрзЗрж╢ржи ржкрзНрж░ржХрзНрж░рж┐рзЯрж╛рзЯ ржЧрж╛ржЗржб ржХрж░рж╛ ржУ ржпрзЗржХрзЛржирзЛ ржкрзНрж░рж╢рзНржи ржмрж╛ рж╕ржорж╕рзНржпрж╛рж░ рж╕ржорж╛ржзрж╛ржи ржжрзЗржУрзЯрж╛ред рзи. ржорж╛рж░рзНржХрзЗржЯрж┐ржВ ржХрзМрж╢рж▓ рждрзИрж░рж┐: ржорж╛рж░рзНржХрзЗржЯрж┐ржВ ржЯрж┐ржорзЗрж░ рж╕ржЩрзНржЧрзЗ ржорж┐рж▓рзЗ ржирждрзБржи ржХрзНрж▓рж╛рзЯрзЗржирзНржЯ ржЖржХрж░рзНрж╖ржгрзЗрж░ ржЬржирзНржп ржХрж╛рж░рзНржпржХрж░ ржорж╛рж░рзНржХрзЗржЯрж┐ржВ ржкрзНрж▓рзНржпрж╛ржи рждрзИрж░рж┐ ржУ ржмрж╛рж╕рзНрждржмрж╛рзЯржи ржХрж░рж╛ред ржорж╛рж░рзНржХрзЗржЯ ржЯрзНрж░рзЗржирзНржб ржУ ржкрзНрж░рждрж┐ржпрзЛржЧрзАржжрзЗрж░ ржХрж╛рж░рзНржпржХрзНрж░ржо ржмрж┐рж╢рзНрж▓рзЗрж╖ржг ржХрж░рзЗ ржЙржирзНржирждрж┐рж░ рж╕рзБржпрзЛржЧ ржЦрзБржБржЬрзЗ ржмрзЗрж░ ржХрж░рж╛ред рзй. рж╕рж╛рж░рзНржнрж┐рж╕ ржкрзНрж░ржорзЛрж╢ржи: ржнрж┐рж╕рж╛ ржкрзНрж░рж╕рзЗрж╕рж┐ржВ рж╕рж╛рж░рзНржнрж┐рж╕рзЗрж░ рж╕рзБржмрж┐ржзрж╛ржЧрзБрж▓рзЛ рж╕рж╣ржЬ ржнрж╛рж╖рж╛рзЯ ржмрзЛржЭрж╛рждрзЗ ржЖржХрж░рзНрж╖ржгрзАрзЯ ржмрзНрж░рзЛрж╢рж┐ржУрж░, ржкрзНрж░рзЗржЬрзЗржи"
  },
  {
    "url": "https://app.shomvob.co/single-job-description/?id=20335",
    "job_id": "20335",
    "company_name": "Chaldal Ltd",
    "job_title": "ржбрзЗрж▓рж┐ржнрж╛рж░рж┐ ржорзНржпрж╛ржи(рж╕рж╛ржЗржХрзЗрж▓рж┐рж╕рзНржЯ)",
    "location": "Banani, Badda, Mirpur, Rajarbagh, Lalmatia",
    "salary": "TK. 9,834-13,434",
    "experience": "Fresher",
    "education": "Any",
    "employment_type": "Full Time",
    "working_hours": "12 hours per day",
    "deadline": "2026-03-07",
    "date_posted": "2026-02-07",
    "industry": "Deliveryman",
    "vacancy": 30,
    "shift": "Day Shift",
    "country": null,
    "company_address": "Banani, Dhaka",
    "job_description": "Responsibilities: Badda, Rajarbagh, Mirpur, Lalmatia, Banani (Chairman Bari), there are vacancies in these areas.\n\nSalary:\nCyclist: 9,834 - 13,434 taka. (Having a bicycle is necessary)\n- Shifts from 7 am, 9 am, and 10:45 am.\n- 12 hours duty.\n- 1 day off every 3 days, 8 days off per month.\n- Monthly mobile bill provided.\n- Delivery bonus:\n- 10 taka bonus for each delivery from 18 to 24.\n- 15 taka bonus for all deliveries after 24.\nIncentive arrangement is available.\nOther facilities:\n- Salary increment after six months.\n- Festival allowance given twice a year.\n- 14 days sick leave per year from six months onwards.\n- 11 days festival leave per year from six months onwards.\n- 12 days paid leave per year from six months onwards.\n- 10 days casual leave per year from six months onwards.\n\nTo join, contact today:\n01401153402\n\nRequirements: Terms and Conditions:\nCyclist must have a bicycle in the post.\nMust be 18 years old.\n\nржмрж╛ржбрзНржбрж╛, рж░рж╛ржЬрж╛рж░ржмрж╛ржЧ, ржорж┐рж░ржкрзБрж░, рж▓рж╛рж▓ржорж╛ржЯрж┐ржпрж╝рж╛, ржмржирж╛ржирзА(ржЪрзЗржпрж╝рж╛рж░ржорзНржпрж╛ржи ржмрж╛ржбрж╝рж┐), ржПржЗ ржПрж░рж┐ржпрж╝рж╛ржЧрзБрж▓рзЛрждрзЗ ржнрзНржпрж╛ржХрзЗржирзНрж╕рж┐ ржЖржЫрзЗ. ржмрзЗрждржи: рж╕рж╛ржЗржХрзНрж▓рж┐рж╕рзНржЯржГ рзп,рзорзйрзк - рззрзй,рзкрзйрзк ржЯрж╛ржХрж╛ред (рж╕рж╛ржЗржХрзЗрж▓ ржерж╛ржХрж╛ ржЖржмрж╢рзНржпржХ) ┬╖ рж╕ржХрж╛рж▓ рзнржЯрж╛ , рзпржЯрж╛ ржПржмржВ рззрзж:рзкрзл ржерзЗржХрзЗ рж╢рж┐ржлржЯред рззрзи ржШржирзНржЯрж╛ ржбрж┐ржЙржЯрж┐ ред ┬╖ рзй ржжрж┐ржи ржкрж░ ржкрж░ рзз ржжрж┐ржи ржЫрзБржЯрж┐, ржорж╛рж╕рзЗ рзо ржжрж┐ржи ржЫрзБржЯрж┐ . ржорж╛рж╕рж┐ржХ ржорзЛржмрж╛ржЗрж▓ ржмрж┐рж▓ ржкрзНрж░ржжрж╛ржи ржХрж░рж╛ рж╣рзЯред -> ржбрзЗрж▓рж┐ржнрж╛рж░рж┐ ржмрзЛржирж╛рж╕ржГ ┬╖ рззрзо ржерзЗржХрзЗ рзирзк ржкрзНрж░рждрж┐ржЯрж┐ ржбрзЗрж▓рж┐ржнрж╛рж░рж┐рж░ ржПрж░ ржЬржирзНржп рззрзж ржЯрж╛ржХрж╛ ржХрж░рзЗ ржмрзЛржирж╛рж╕, ┬╖ рзирзк ржПрж░ ржкрж░ рж╕ржХрж▓ ржбрзЗрж▓рж┐ржнрж╛рж░рж┐ ржПрж░ ржЬржирзНржп рззрзл ржЯрж╛ржХрж╛ ржХрж░рзЗ ржмрзЛржирж╛рж╕ред ржЗржирж╕рзЗржирзНржЯрж┐ржн ржПрж░ ржмрзНржпржмрж╕рзНржерж╛ рж░ржпрж╝рзЗржЫрзЗ ->ржЕржирзНржпрж╛ржирзНржп рж╕рзБржмрж┐ржзрж╛ рж╕ржорзБрж╣ржГ ┬╖ ржЫржпрж╝ ржорж╛рж╕ ржкрж░ ржмрзЗрждржи ржмрзГржжрзНржзрж┐ ржкрж╛ржмрзЗред ┬╖ ржмржЫрж░рзЗ ржжрзБржЗржмрж╛рж░ ржЙрзОрж╕ржм ржнрж╛рждрж╛ ржжрзЗржпрж╝рж╛ рж╣ржпрж╝ред ┬╖ ржЫржпрж╝ ржорж╛рж╕ ржкрж░ ржерзЗржХрзЗ ржмржЫрж░рзЗ рззрзк ржжрж┐ржи ржЕрж╕рзБрж╕рзНржерждрж╛ ржЬржирж┐ржд ржЫрзБржЯрж┐ ржжрзЗржпрж╝рж╛ рж╣ржпрж╝ред ┬╖ ржЫржпрж╝ ржорж╛рж╕ ржкрж░ ржерзЗржХрзЗ ржмржЫрж░рзЗ рззрзз ржжрж┐ржи ржЙрзОрж╕ржм ржЫрзБржЯрж┐ ржжрзЗржпрж╝рж╛ рж╣ржпрж╝ред ┬╖ ржЫржпрж╝ ржорж╛рж╕ ржкрж░ ржерзЗржХрзЗ ржмржЫрж░рзЗ рззрзи ржжрж┐ржи ржмрзЗрждржиржнрзЛржЧрзА ржЫрзБржЯрж┐ ржжрзЗржпрж╝рж╛ рж╣ржпрж╝ред ┬╖ ржЫржпрж╝ ржорж╛рж╕ ржкрж░ ржерзЗржХрзЗ ржмржЫрж░рзЗ рззрзж ржжрж┐ржи ржирзИржорж┐рждрзНрждрж┐ржХ ржЫрзБржЯрж┐ ржжрзЗржпрж╝рж╛ рж╣ржпрж╝ ржпрзЛржЧржжрж╛ржи ржХрж░рждрзЗ ржЖржЬржЗ ржЖржЬ ржЗ ржпрзЛржЧрж╛ржпрзЛржЧ ржХрж░рзБржи: 01401153402"
  }
]